pixelterm/__init__.py
pixelterm/cursor_utils.py
pixelterm/font.py
pixelterm/frame.py
pixelterm/pixelterm_types.py
pixelterm/render_utils.py
pixelterm/fonts/font1.png
pixelterm-1.0.5.dist-info/METADATA
pixelterm-1.0.5.dist-info/WHEEL
pixelterm-1.0.5.dist-info/licenses/LICENSE
pixelterm-1.0.5.dist-info/RECORD
