Metadata-Version: 2.3
Name: pixelterm
Version: 1.0.5
Summary: Terminal Graphics Rendering Library
Project-URL: Homepage, https://github.com/crystaltine/pixelterm
Project-URL: Repository, https://github.com/crystaltine/pixelterm
Project-URL: Issues, https://github.com/crystaltine/pixelterm/issues
Author-email: crystaltine <msh379c@outlook.com>
License-File: LICENSE
Keywords: ansi,ascii,console,graphics,rendering,terminal
Classifier: License :: OSI Approved :: MIT License
Classifier: Operating System :: Microsoft :: Windows
Classifier: Programming Language :: Python :: 3
Requires-Python: >=3.10
Requires-Dist: numpy
Requires-Dist: pillow
Requires-Dist: scikit-image
